fluentm/__init__.py
fluentm/entities.py
fluentm/renderer.py
fluentm/templates/report.html
fluentm-0.0.21.dist-info/LICENSE
fluentm-0.0.21.dist-info/METADATA
fluentm-0.0.21.dist-info/WHEEL
fluentm-0.0.21.dist-info/top_level.txt
fluentm-0.0.21.dist-info/RECORD
