Metadata-Version: 2.1
Name: fluentm
Version: 0.0.21
Summary: Architecture descriptions as code
Home-page: https://github.com/hyakuhei/fluentm
Author: hyakuhei
Author-email: hyakuhei@gmail.com
License: UNKNOWN
Platform: UNKNOWN
Classifier: Programming Language :: Python :: 3
Classifier: License :: OSI Approved :: Apache Software License
Classifier: Operating System :: OS Independent
Requires-Python: >=3.7
License-File: LICENSE
Requires-Dist: graphviz (==0.16)
Requires-Dist: Jinja2 (==3.0.1)
